setup.py
graph_nets/__init__.py
graph_nets/blocks.py
graph_nets/graphs.py
graph_nets/modules.py
graph_nets/utils_np.py
graph_nets/utils_tf.py
graph_nets.egg-info/PKG-INFO
graph_nets.egg-info/SOURCES.txt
graph_nets.egg-info/dependency_links.txt
graph_nets.egg-info/requires.txt
graph_nets.egg-info/top_level.txt
graph_nets/demos/__init__.py
graph_nets/demos/models.py
graph_nets/tests/__init__.py
graph_nets/tests/blocks_test.py
graph_nets/tests/graphs_test.py
graph_nets/tests/modules_test.py
graph_nets/tests/test_utils.py
graph_nets/tests/utils_np_test.py
graph_nets/tests/utils_tf_test.py